.gitattributes
.gitignore
LICENSE.txt
run_all_tests.py
setup.cfg
setup.py
onyx/__init__.py
onyx.scheduler.egg-info/PKG-INFO
onyx.scheduler.egg-info/SOURCES.txt
onyx.scheduler.egg-info/dependency_links.txt
onyx.scheduler.egg-info/entry_points.txt
onyx.scheduler.egg-info/namespace_packages.txt
onyx.scheduler.egg-info/not-zip-safe
onyx.scheduler.egg-info/requires.txt
onyx.scheduler.egg-info/top_level.txt
onyx/scheduler/__init__.py
onyx/scheduler/jobsched_fns.py
onyx/scheduler/jobsched_server.py
onyx/scheduler/proc_example.py