Metadata-Version: 1.1
Name: onyx.scheduler
Version: 1.0.0
Summary: Job scheduling extension for onyx.
Home-page: https://github.com/sbraccia/onyx.scheduler
Author: carlo sbraccia
Author-email: carlo.sbraccia@gmail.com
License: UNKNOWN
Platform: UNKNOWN
Classifier: Development Status :: 4 - Beta
Classifier: Environment :: Console
Classifier: Intended Audience :: Developers
Classifier: Intended Audience :: Financial and Insurance Industry
Classifier: License :: OSI Approved :: Apache Software License
Classifier: Natural Language :: English
Classifier: Operating System :: OS Independent
Classifier: Programming Language :: Python :: 3.5
Classifier: Topic :: Software Development :: Libraries :: Python Modules
Classifier: Topic :: Software Development :: Libraries :: Application Frameworks
